{
  "geography": "state_senate_district",
  "level": "state_senate_district",
  "jurisdiction_name": "25",
  "updated": "2026-05-09",
  "generated_by": "templated-v1",
  "template_version": "v2",
  "config_version": "v1",
  "metrics_hash": "f67e743266ad8c6b",
  "narrative": "25 Ohio Senate district has 221,431 registered voters, with 61.9% unaffiliated or lacking primary history. Republican-leaning voters make up 14.1% of registrants and Democratic-leaning voters account for 24.0%, a clear Democratic lean of 9.9 percentage points.\n\nElected representation:\n  State Senator: data not yet available."
}