{
  "title": "Party Affiliation",
  "type": "doughnut",
  "chartConfig": {
    "labels": [
      "Pure R — 195 (17%)",
      "UNC – Lapsed R — 103 (9%)",
      "Mixed – Active — 107 (9%)",
      "Mixed – Lapsed — 77 (7%)",
      "UNC – No Primary — 480 (42%)",
      "UNC – Lapsed D — 131 (11%)",
      "Pure D — 63 (5%)"
    ],
    "datasets": [
      {
        "data": [
          195,
          103,
          107,
          77,
          480,
          131,
          63
        ],
        "backgroundColor": [
          "#ef4444",
          "#fca5a5",
          "#f59e0b",
          "#a78bfa",
          "#9ca3af",
          "#93c5fd",
          "#3b82f6"
        ]
      }
    ]
  },
  "note": "Analysis run 2026-05-10 — Ohio Secretary of State SWVF voter file — partisan spectrum: registered + behavioral cohorts.",
  "geography": "Village",
  "jurisdiction_name": "MINERVA VILLAGE (Stark Co.)",
  "updated": "2026-05-10"
}