{
  "title": "Party Affiliation",
  "type": "doughnut",
  "chartConfig": {
    "labels": [
      "Pure R — 500 (19%)",
      "UNC – Lapsed R — 460 (18%)",
      "Mixed – Active — 209 (8%)",
      "Mixed – Lapsed — 191 (7%)",
      "UNC – No Primary — 1,029 (39%)",
      "UNC – Lapsed D — 170 (6%)",
      "Pure D — 57 (2%)"
    ],
    "datasets": [
      {
        "data": [
          500,
          460,
          209,
          191,
          1029,
          170,
          57
        ],
        "backgroundColor": [
          "#ef4444",
          "#fca5a5",
          "#f59e0b",
          "#a78bfa",
          "#9ca3af",
          "#93c5fd",
          "#3b82f6"
        ]
      }
    ]
  },
  "note": "Analysis run 2026-07-10 — Ohio Secretary of State SWVF voter file — partisan spectrum: affiliated + behavioral cohorts.",
  "geography": "Local School District",
  "jurisdiction_name": "EDGERTON LOCAL SD (WILLIAMS)",
  "updated": "2026-07-10"
}