{
  "geography": "local_school_district",
  "level": "local_school_district",
  "jurisdiction_name": "LAKEWOOD LOCAL LOCAL  SD (LICKING)",
  "updated": "2026-05-09",
  "generated_by": "templated-v1",
  "template_version": "v2",
  "config_version": "v1",
  "metrics_hash": "64276fd807691a79",
  "narrative": "Lakewood Local Local  Sd (Licking) school district has 10,505 registered voters, with 53.5% unaffiliated or lacking primary history. Republican-leaning voters make up 33.5% of registrants and Democratic-leaning voters account for 12.9%, a pronounced Republican lean of 20.6 percentage points.\n\nElected representation:\n  School Board: data not yet available."
}