{
  "title": "UNC Shadow Partisanship",
  "type": "doughnut",
  "chartConfig": {
    "labels": [
      "UNC – Lapsed R — 226",
      "Mixed – Active — 162",
      "Mixed – Lapsed — 182",
      "UNC – No Primary — 2,071",
      "UNC – Lapsed D — 499"
    ],
    "datasets": [
      {
        "data": [
          226,
          162,
          182,
          2071,
          499
        ],
        "backgroundColor": [
          "#fca5a5",
          "#f59e0b",
          "#a78bfa",
          "#9ca3af",
          "#93c5fd"
        ]
      }
    ]
  },
  "note": "Analysis run 2026-05-29 — Ohio Secretary of State SWVF voter file",
  "geography": "Ward",
  "jurisdiction_name": "DAYTON WARD 12",
  "updated": "2026-05-29"
}