{
  "title": "Party Affiliation",
  "type": "doughnut",
  "chartConfig": {
    "labels": [
      "Pure R — 326 (21%)",
      "UNC – Lapsed R — 226 (15%)",
      "Mixed – Active — 161 (11%)",
      "Mixed – Lapsed — 140 (9%)",
      "UNC – No Primary — 484 (32%)",
      "UNC – Lapsed D — 111 (7%)",
      "Pure D — 81 (5%)"
    ],
    "datasets": [
      {
        "data": [
          326,
          226,
          161,
          140,
          484,
          111,
          81
        ],
        "backgroundColor": [
          "#ef4444",
          "#fca5a5",
          "#f59e0b",
          "#a78bfa",
          "#9ca3af",
          "#93c5fd",
          "#3b82f6"
        ]
      }
    ]
  },
  "note": "Analysis run 2026-07-16 — Ohio Secretary of State SWVF voter file — partisan spectrum: affiliated + behavioral cohorts.",
  "geography": "Ward",
  "jurisdiction_name": "LONDON WARD 2 (LONDON City)",
  "updated": "2026-07-16"
}