{
  "title": "Party Affiliation by Birth Decade",
  "type": "bar",
  "chartConfig": {
    "labels": [
      "1920s",
      "1930s",
      "1940s",
      "1950s",
      "1960s",
      "1970s",
      "1980s",
      "1990s",
      "2000s"
    ],
    "datasets": [
      {
        "label": "Pure R",
        "data": [
          1,
          10,
          45,
          71,
          65,
          69,
          55,
          28,
          20
        ],
        "backgroundColor": "#ef4444",
        "stack": "r_pure"
      },
      {
        "label": "UNC – Lapsed R",
        "data": [
          1,
          8,
          24,
          43,
          69,
          85,
          72,
          47,
          3
        ],
        "backgroundColor": "#fca5a5",
        "stack": "unc_r"
      },
      {
        "label": "Mixed – Active",
        "data": [
          1,
          28,
          96,
          147,
          146,
          88,
          58,
          12,
          1
        ],
        "backgroundColor": "#f59e0b",
        "stack": "unc_mid"
      },
      {
        "label": "Mixed – Lapsed",
        "data": [
          2,
          10,
          37,
          55,
          77,
          78,
          53,
          20,
          8
        ],
        "backgroundColor": "#a78bfa",
        "stack": "unc_mid"
      },
      {
        "label": "UNC – No Primary",
        "data": [
          1,
          17,
          71,
          147,
          229,
          328,
          455,
          554,
          535
        ],
        "backgroundColor": "#9ca3af",
        "stack": "unc_mid"
      },
      {
        "label": "UNC – Lapsed D",
        "data": [
          3,
          34,
          77,
          139,
          192,
          221,
          171,
          109,
          13
        ],
        "backgroundColor": "#93c5fd",
        "stack": "unc_d"
      },
      {
        "label": "Pure D",
        "data": [
          1,
          38,
          121,
          217,
          186,
          145,
          103,
          43,
          37
        ],
        "backgroundColor": "#3b82f6",
        "stack": "d_pure"
      }
    ]
  },
  "note": "Analysis run 2026-05-29 — Ohio Secretary of State SWVF voter file",
  "geography": "Ward",
  "jurisdiction_name": "LORAIN CITY WARD-8",
  "updated": "2026-05-29"
}