{
  "title": "UNC Shadow Partisanship",
  "type": "doughnut",
  "chartConfig": {
    "labels": [
      "UNC – Lapsed R — 109",
      "Mixed – Active — 113",
      "Mixed – Lapsed — 119",
      "UNC – No Primary — 494",
      "UNC – Lapsed D — 219"
    ],
    "datasets": [
      {
        "data": [
          109,
          113,
          119,
          494,
          219
        ],
        "backgroundColor": [
          "#fca5a5",
          "#f59e0b",
          "#a78bfa",
          "#9ca3af",
          "#93c5fd"
        ]
      }
    ]
  },
  "note": "Analysis run 2026-05-29 — Ohio Secretary of State SWVF voter file",
  "geography": "Ward",
  "jurisdiction_name": "M-O-L WARD 4",
  "updated": "2026-05-29"
}