{
  "title": "Party Affiliation by Birth Decade",
  "type": "bar",
  "chartConfig": {
    "labels": [
      "1910s",
      "1920s",
      "1930s",
      "1940s",
      "1950s",
      "1960s",
      "1970s",
      "1980s",
      "1990s",
      "2000s"
    ],
    "datasets": [
      {
        "label": "Pure R",
        "data": [
          0,
          19,
          356,
          1373,
          2488,
          2428,
          1448,
          971,
          495,
          279
        ],
        "backgroundColor": "#ef4444",
        "stack": "r_pure"
      },
      {
        "label": "UNC – Lapsed R",
        "data": [
          0,
          24,
          265,
          613,
          1401,
          2361,
          2088,
          1922,
          1480,
          159
        ],
        "backgroundColor": "#fca5a5",
        "stack": "unc_r"
      },
      {
        "label": "Mixed – Active",
        "data": [
          0,
          5,
          156,
          839,
          1633,
          1353,
          926,
          628,
          248,
          25
        ],
        "backgroundColor": "#f59e0b",
        "stack": "unc_mid"
      },
      {
        "label": "Mixed – Lapsed",
        "data": [
          0,
          9,
          144,
          510,
          1063,
          1442,
          1522,
          1255,
          714,
          371
        ],
        "backgroundColor": "#a78bfa",
        "stack": "unc_mid"
      },
      {
        "label": "UNC – No Primary",
        "data": [
          0,
          16,
          211,
          744,
          1594,
          2927,
          4698,
          7264,
          11571,
          8986
        ],
        "backgroundColor": "#9ca3af",
        "stack": "unc_mid"
      },
      {
        "label": "UNC – Lapsed D",
        "data": [
          1,
          16,
          176,
          561,
          1116,
          1574,
          2078,
          2292,
          1883,
          286
        ],
        "backgroundColor": "#93c5fd",
        "stack": "unc_d"
      },
      {
        "label": "Pure D",
        "data": [
          0,
          9,
          114,
          649,
          1227,
          907,
          1067,
          1114,
          941,
          456
        ],
        "backgroundColor": "#3b82f6",
        "stack": "d_pure"
      }
    ]
  },
  "note": "Analysis run 2026-05-09 — Ohio Secretary of State SWVF voter file",
  "geography": "State Representative District",
  "jurisdiction_name": "11",
  "updated": "2026-05-09"
}