{
  "geography": "state_representative_district",
  "level": "state_representative_district",
  "jurisdiction_name": "52",
  "updated": "2026-05-09",
  "generated_by": "templated-v1",
  "template_version": "v2",
  "config_version": "v1",
  "metrics_hash": "e9796d7a72fa3cb1",
  "narrative": "52 Ohio House district has 83,901 registered voters, with 57.8% unaffiliated or lacking primary history. Republican-leaning voters make up 18.5% of registrants and Democratic-leaning voters account for 23.7%, a modest Democratic lean of 5.3 percentage points.\n\nElected representation:\n  State Representative: data not yet available."
}