{
  "title": "UNC Shadow Partisanship",
  "type": "doughnut",
  "chartConfig": {
    "labels": [
      "UNC – Lapsed R — 157",
      "Mixed – Active — 93",
      "Mixed – Lapsed — 89",
      "UNC – No Primary — 290",
      "UNC – Lapsed D — 61"
    ],
    "datasets": [
      {
        "data": [
          157,
          93,
          89,
          290,
          61
        ],
        "backgroundColor": [
          "#fca5a5",
          "#f59e0b",
          "#a78bfa",
          "#9ca3af",
          "#93c5fd"
        ]
      }
    ]
  },
  "note": "Analysis run 2026-05-10 — Ohio Secretary of State SWVF voter file",
  "geography": "Township",
  "jurisdiction_name": "GREENFIELD TOWNSHIP (Huron Co.)",
  "updated": "2026-05-10"
}