{
  "title": "UNC Shadow Partisanship",
  "type": "doughnut",
  "chartConfig": {
    "labels": [
      "UNC – Lapsed R — 180",
      "Mixed – Active — 110",
      "Mixed – Lapsed — 77",
      "UNC – No Primary — 609",
      "UNC – Lapsed D — 107"
    ],
    "datasets": [
      {
        "data": [
          180,
          110,
          77,
          609,
          107
        ],
        "backgroundColor": [
          "#fca5a5",
          "#f59e0b",
          "#a78bfa",
          "#9ca3af",
          "#93c5fd"
        ]
      }
    ]
  },
  "note": "Analysis run 2026-05-10 — Ohio Secretary of State SWVF voter file",
  "geography": "Township",
  "jurisdiction_name": "MARY ANN TWP (Licking Co.)",
  "updated": "2026-05-10"
}