{
  "geography": "township",
  "level": "township",
  "jurisdiction_name": "MONROE TOWNSHIP (Perry Co.)",
  "updated": "2026-05-10",
  "generated_by": "templated-v1",
  "template_version": "v2",
  "config_version": "v1",
  "metrics_hash": "e3ba8abbd4b3717a",
  "narrative": "Monroe Township has 795 registered voters, with 57.1% unaffiliated or lacking primary history. Republican-leaning voters make up 24.0% of registrants and Democratic-leaning voters account for 18.9%, a modest Republican lean of 5.2 percentage points.\n\nElected representation:\n  Township Trustee: data not yet available.\n  Fiscal Officer: data not yet available."
}