{
  "title": "UNC Shadow Partisanship",
  "type": "doughnut",
  "chartConfig": {
    "labels": [
      "UNC – Lapsed R — 34",
      "Mixed – Active — 55",
      "Mixed – Lapsed — 45",
      "UNC – No Primary — 174",
      "UNC – Lapsed D — 48"
    ],
    "datasets": [
      {
        "data": [
          34,
          55,
          45,
          174,
          48
        ],
        "backgroundColor": [
          "#fca5a5",
          "#f59e0b",
          "#a78bfa",
          "#9ca3af",
          "#93c5fd"
        ]
      }
    ]
  },
  "note": "Analysis run 2026-05-10 — Ohio Secretary of State SWVF voter file",
  "geography": "Township",
  "jurisdiction_name": "COLEBROOK TWP (Unknown Co.)",
  "updated": "2026-05-10"
}