{
  "title": "Party Affiliation by Generation — PRECINCT ORANGE P",
  "county": "Delaware",
  "precinct": "PRECINCT ORANGE P",
  "geography": "precinct-detail",
  "type": "bar",
  "updated": "2026-05-09",
  "note": "Pew Research Center generational boundaries",
  "chartConfig": {
    "labels": [
      "Silent/Greatest",
      "Baby Boomers",
      "Gen X",
      "Millennials",
      "Gen Z"
    ],
    "datasets": [
      {
        "label": "Pure R",
        "data": [
          11,
          90,
          99,
          16,
          24
        ],
        "backgroundColor": "#ef4444",
        "borderRadius": 2,
        "stack": "r_pure"
      },
      {
        "label": "UNC – Lapsed R",
        "data": [
          6,
          27,
          60,
          38,
          6
        ],
        "backgroundColor": "#fca5a5",
        "borderRadius": 2,
        "stack": "unc_r"
      },
      {
        "label": "Mixed – Active",
        "data": [
          4,
          39,
          45,
          13,
          0
        ],
        "backgroundColor": "#f59e0b",
        "borderRadius": 2,
        "stack": "unc_mid"
      },
      {
        "label": "Mixed – Lapsed",
        "data": [
          2,
          19,
          39,
          17,
          11
        ],
        "backgroundColor": "#a78bfa",
        "borderRadius": 2,
        "stack": "unc_mid"
      },
      {
        "label": "UNC – No Primary",
        "data": [
          1,
          21,
          100,
          82,
          162
        ],
        "backgroundColor": "#9ca3af",
        "borderRadius": 2,
        "stack": "unc_mid"
      },
      {
        "label": "UNC – Lapsed D",
        "data": [
          7,
          17,
          40,
          30,
          5
        ],
        "backgroundColor": "#93c5fd",
        "borderRadius": 2,
        "stack": "unc_d"
      },
      {
        "label": "Pure D",
        "data": [
          3,
          28,
          42,
          19,
          13
        ],
        "backgroundColor": "#3b82f6",
        "borderRadius": 2,
        "stack": "d_pure"
      }
    ]
  }
}