{
  "title": "Party Affiliation by Generation — PICKERINGTON CITY Q",
  "county": "Fairfield",
  "precinct": "PICKERINGTON CITY Q",
  "geography": "precinct-detail",
  "type": "bar",
  "updated": "2026-07-15",
  "note": "Pew Research Center generational boundaries",
  "chartConfig": {
    "labels": [
      "Silent/Greatest",
      "Baby Boomers",
      "Gen X",
      "Millennials",
      "Gen Z"
    ],
    "datasets": [
      {
        "label": "Pure R",
        "data": [
          3,
          26,
          53,
          17,
          3
        ],
        "backgroundColor": "#ef4444",
        "borderRadius": 2,
        "stack": "r_pure"
      },
      {
        "label": "UNC – Lapsed R",
        "data": [
          3,
          9,
          38,
          14,
          3
        ],
        "backgroundColor": "#fca5a5",
        "borderRadius": 2,
        "stack": "unc_r"
      },
      {
        "label": "Mixed – Active",
        "data": [
          1,
          13,
          16,
          9,
          1
        ],
        "backgroundColor": "#f59e0b",
        "borderRadius": 2,
        "stack": "unc_mid"
      },
      {
        "label": "Mixed – Lapsed",
        "data": [
          0,
          19,
          32,
          21,
          9
        ],
        "backgroundColor": "#a78bfa",
        "borderRadius": 2,
        "stack": "unc_mid"
      },
      {
        "label": "UNC – No Primary",
        "data": [
          3,
          41,
          146,
          209,
          199
        ],
        "backgroundColor": "#9ca3af",
        "borderRadius": 2,
        "stack": "unc_mid"
      },
      {
        "label": "UNC – Lapsed D",
        "data": [
          1,
          21,
          60,
          21,
          3
        ],
        "backgroundColor": "#93c5fd",
        "borderRadius": 2,
        "stack": "unc_d"
      },
      {
        "label": "Pure D",
        "data": [
          0,
          37,
          59,
          39,
          16
        ],
        "backgroundColor": "#3b82f6",
        "borderRadius": 2,
        "stack": "d_pure"
      }
    ]
  }
}