{
  "title": "Party Affiliation by Generation — UA 4-B",
  "county": "Franklin",
  "precinct": "UA 4-B",
  "geography": "precinct-detail",
  "type": "bar",
  "updated": "2026-07-14",
  "note": "Pew Research Center generational boundaries",
  "chartConfig": {
    "labels": [
      "Silent/Greatest",
      "Baby Boomers",
      "Gen X",
      "Millennials",
      "Gen Z"
    ],
    "datasets": [
      {
        "label": "Pure R",
        "data": [
          9,
          40,
          14,
          9,
          1
        ],
        "backgroundColor": "#ef4444",
        "borderRadius": 2,
        "stack": "r_pure"
      },
      {
        "label": "UNC – Lapsed R",
        "data": [
          13,
          24,
          39,
          40,
          1
        ],
        "backgroundColor": "#fca5a5",
        "borderRadius": 2,
        "stack": "unc_r"
      },
      {
        "label": "Mixed – Active",
        "data": [
          7,
          37,
          30,
          21,
          0
        ],
        "backgroundColor": "#f59e0b",
        "borderRadius": 2,
        "stack": "unc_mid"
      },
      {
        "label": "Mixed – Lapsed",
        "data": [
          10,
          27,
          35,
          37,
          3
        ],
        "backgroundColor": "#a78bfa",
        "borderRadius": 2,
        "stack": "unc_mid"
      },
      {
        "label": "UNC – No Primary",
        "data": [
          3,
          24,
          48,
          159,
          98
        ],
        "backgroundColor": "#9ca3af",
        "borderRadius": 2,
        "stack": "unc_mid"
      },
      {
        "label": "UNC – Lapsed D",
        "data": [
          5,
          24,
          48,
          72,
          8
        ],
        "backgroundColor": "#93c5fd",
        "borderRadius": 2,
        "stack": "unc_d"
      },
      {
        "label": "Pure D",
        "data": [
          8,
          45,
          60,
          70,
          15
        ],
        "backgroundColor": "#3b82f6",
        "borderRadius": 2,
        "stack": "d_pure"
      }
    ]
  }
}