{
  "title": "Party Affiliation \u2014 COLS 44-A",
  "county": "Franklin",
  "precinct": "COLS 44-A",
  "geography": "precinct-detail",
  "type": "doughnut",
  "updated": "2026-05-06",
  "chartConfig": {
    "labels": [
      "REP",
      "UNC \u2013 Lifetime R",
      "DEM",
      "UNC \u2013 Lifetime D",
      "UNC \u2013 Mixed",
      "UNC \u2013 No History"
    ],
    "datasets": [
      {
        "data": [
          24,
          20,
          152,
          277,
          38,
          738
        ],
        "backgroundColor": [
          "#ef4444",
          "#f87171",
          "#3b82f6",
          "#60a5fa",
          "#a78bfa",
          "#9ca3af"
        ],
        "borderWidth": 2,
        "borderColor": "transparent"
      }
    ]
  }
}