{
  "geography": "precinct",
  "level": "precinct",
  "jurisdiction_name": "NEW ALBANY-F",
  "updated": "2026-05-09",
  "generated_by": "templated-v1",
  "template_version": "v2",
  "config_version": "v1",
  "metrics_hash": "933fdd57339b906e",
  "narrative": "New Albany-F (precinct in Franklin County) has 1,709 registered voters, with 51.7% unaffiliated or lacking primary history. Republican-leaning voters make up 27.9% of registrants and Democratic-leaning voters account for 20.4%, a clear Republican lean of 7.4 percentage points.\n\nElected representation:\n  Republican Precinct Captain: data not yet available.\n  Democratic Precinct Captain: data not yet available."
}