{
  "geography": "precinct",
  "level": "precinct",
  "jurisdiction_name": "INDIAN HILL C",
  "updated": "2026-05-28",
  "generated_by": "templated-v1",
  "template_version": "v2",
  "config_version": "v1",
  "metrics_hash": "e4fe8abeaa185144",
  "narrative": "Indian Hill C (precinct in Hamilton County) has 887 registered voters, with 50.4% unaffiliated or lacking primary history. Republican-leaning voters make up 38.2% of registrants and Democratic-leaning voters account for 11.4%, a pronounced Republican lean of 26.8 percentage points.\n\nElected representation:\n  Republican Precinct Captain: data not yet available.\n  Democratic Precinct Captain: data not yet available."
}