{
  "geography": "precinct",
  "level": "precinct",
  "jurisdiction_name": "HARR TWP BB",
  "updated": "2026-05-29",
  "generated_by": "templated-v1",
  "template_version": "v2",
  "config_version": "v1",
  "metrics_hash": "396443c3e071da86",
  "narrative": "Harr Twp Bb (precinct in Hamilton County) has 1,324 registered voters, with 50.5% unaffiliated or lacking primary history. Republican-leaning voters make up 40.4% of registrants and Democratic-leaning voters account for 9.1%, a pronounced Republican lean of 31.3 percentage points.\n\nElected representation:\n  Republican Precinct Captain: data not yet available.\n  Democratic Precinct Captain: data not yet available."
}