{
  "title": "Party Affiliation by Generation",
  "county": "Hancock",
  "geography": "county",
  "type": "bar",
  "updated": "2026-05-28",
  "note": "Analysis run 2026-05-28 — Ohio Secretary of State SWVF voter file — Pew Research Center generational boundaries",
  "chartConfig": {
    "labels": [
      "Silent/Greatest",
      "Baby Boomers",
      "Gen X",
      "Millennials",
      "Gen Z"
    ],
    "datasets": [
      {
        "label": "Pure R",
        "data": [
          1331,
          5578,
          3555,
          2099,
          879
        ],
        "backgroundColor": "#ef4444",
        "borderRadius": 2,
        "stack": "r_pure"
      },
      {
        "label": "UNC – Lapsed R",
        "data": [
          456,
          1717,
          1789,
          1574,
          393
        ],
        "backgroundColor": "#fca5a5",
        "borderRadius": 2,
        "stack": "unc_r"
      },
      {
        "label": "Mixed – Active",
        "data": [
          432,
          1938,
          941,
          538,
          42
        ],
        "backgroundColor": "#f59e0b",
        "borderRadius": 2,
        "stack": "unc_mid"
      },
      {
        "label": "Mixed – Lapsed",
        "data": [
          236,
          943,
          1023,
          1016,
          353
        ],
        "backgroundColor": "#a78bfa",
        "borderRadius": 2,
        "stack": "unc_mid"
      },
      {
        "label": "UNC – No Primary",
        "data": [
          294,
          2176,
          3698,
          6016,
          5815
        ],
        "backgroundColor": "#9ca3af",
        "borderRadius": 2,
        "stack": "unc_mid"
      },
      {
        "label": "UNC – Lapsed D",
        "data": [
          206,
          945,
          893,
          983,
          189
        ],
        "backgroundColor": "#93c5fd",
        "borderRadius": 2,
        "stack": "unc_d"
      },
      {
        "label": "Pure D",
        "data": [
          143,
          719,
          274,
          251,
          111
        ],
        "backgroundColor": "#3b82f6",
        "borderRadius": 2,
        "stack": "d_pure"
      }
    ]
  }
}