{
  "geography": "precinct",
  "level": "precinct",
  "jurisdiction_name": "HOLGATE VILLAGE 19.0",
  "updated": "2026-06-22",
  "generated_by": "templated-v1",
  "template_version": "v2",
  "config_version": "v1",
  "metrics_hash": "9f8a4684353889f5",
  "narrative": "Holgate Village 19.0 (precinct in Henry County) has 677 registered voters, with 57.6% unaffiliated or lacking primary history. Republican-leaning voters make up 26.7% of registrants and Democratic-leaning voters account for 15.7%, a clear Republican lean of 11.1 percentage points.\n\nElected representation:\n  Republican Precinct Captain: data not yet available.\n  Democratic Precinct Captain: data not yet available."
}