{
  "title": "Party Affiliation by Generation — PRECINCT NORWALK 3-C",
  "county": "Huron",
  "precinct": "PRECINCT NORWALK 3-C",
  "geography": "precinct-detail",
  "type": "bar",
  "updated": "2026-06-22",
  "note": "Pew Research Center generational boundaries",
  "chartConfig": {
    "labels": [
      "Silent/Greatest",
      "Baby Boomers",
      "Gen X",
      "Millennials",
      "Gen Z"
    ],
    "datasets": [
      {
        "label": "Pure R",
        "data": [
          25,
          62,
          40,
          20,
          7
        ],
        "backgroundColor": "#ef4444",
        "borderRadius": 2,
        "stack": "r_pure"
      },
      {
        "label": "UNC – Lapsed R",
        "data": [
          6,
          21,
          38,
          15,
          5
        ],
        "backgroundColor": "#fca5a5",
        "borderRadius": 2,
        "stack": "unc_r"
      },
      {
        "label": "Mixed – Active",
        "data": [
          9,
          39,
          16,
          4,
          0
        ],
        "backgroundColor": "#f59e0b",
        "borderRadius": 2,
        "stack": "unc_mid"
      },
      {
        "label": "Mixed – Lapsed",
        "data": [
          5,
          23,
          16,
          18,
          3
        ],
        "backgroundColor": "#a78bfa",
        "borderRadius": 2,
        "stack": "unc_mid"
      },
      {
        "label": "UNC – No Primary",
        "data": [
          8,
          37,
          74,
          121,
          120
        ],
        "backgroundColor": "#9ca3af",
        "borderRadius": 2,
        "stack": "unc_mid"
      },
      {
        "label": "UNC – Lapsed D",
        "data": [
          12,
          26,
          27,
          25,
          3
        ],
        "backgroundColor": "#93c5fd",
        "borderRadius": 2,
        "stack": "unc_d"
      },
      {
        "label": "Pure D",
        "data": [
          11,
          26,
          5,
          5,
          2
        ],
        "backgroundColor": "#3b82f6",
        "borderRadius": 2,
        "stack": "d_pure"
      }
    ]
  }
}