{
  "title": "Party Affiliation by Generation — PRECINCT PAINESVILLE CITY 3B",
  "county": "Lake",
  "precinct": "PRECINCT PAINESVILLE CITY 3B",
  "geography": "precinct-detail",
  "type": "bar",
  "updated": "2026-05-08",
  "note": "Pew Research Center generational boundaries",
  "chartConfig": {
    "labels": [
      "Silent/Greatest",
      "Baby Boomers",
      "Gen X",
      "Millennials",
      "Gen Z"
    ],
    "datasets": [
      {
        "label": "Pure R",
        "data": [
          7,
          40,
          30,
          17,
          3
        ],
        "backgroundColor": "#ef4444",
        "borderRadius": 2,
        "stack": "r_pure"
      },
      {
        "label": "R – Crossover",
        "data": [
          4,
          20,
          12,
          3,
          0
        ],
        "backgroundColor": "#f87171",
        "borderRadius": 2,
        "stack": "r_cross"
      },
      {
        "label": "UNC – Lifetime R",
        "data": [
          3,
          13,
          28,
          8,
          1
        ],
        "backgroundColor": "#fca5a5",
        "borderRadius": 2,
        "stack": "unc"
      },
      {
        "label": "UNC – Mixed",
        "data": [
          4,
          12,
          8,
          3,
          0
        ],
        "backgroundColor": "#a78bfa",
        "borderRadius": 2,
        "stack": "unc"
      },
      {
        "label": "UNC – No History",
        "data": [
          10,
          67,
          104,
          147,
          151
        ],
        "backgroundColor": "#9ca3af",
        "borderRadius": 2,
        "stack": "unc"
      },
      {
        "label": "UNC – Lifetime D",
        "data": [
          9,
          34,
          31,
          26,
          5
        ],
        "backgroundColor": "#93c5fd",
        "borderRadius": 2,
        "stack": "unc"
      },
      {
        "label": "D – Crossover",
        "data": [
          3,
          6,
          6,
          1,
          0
        ],
        "backgroundColor": "#60a5fa",
        "borderRadius": 2,
        "stack": "d_cross"
      },
      {
        "label": "Pure D",
        "data": [
          6,
          33,
          17,
          14,
          6
        ],
        "backgroundColor": "#3b82f6",
        "borderRadius": 2,
        "stack": "d_pure"
      }
    ]
  }
}