{
  "title": "Voter Age Distribution by Birth Decade — PRECINCT SYLVANIA CITY 6",
  "county": "Lucas",
  "precinct": "PRECINCT SYLVANIA CITY 6",
  "geography": "precinct-detail",
  "type": "bar",
  "updated": "2026-07-15",
  "chartConfig": {
    "labels": [
      "1920s",
      "1930s",
      "1940s",
      "1950s",
      "1960s",
      "1970s",
      "1980s",
      "1990s",
      "2000s"
    ],
    "datasets": [
      {
        "label": "Registered Voters",
        "data": [
          5,
          59,
          161,
          207,
          136,
          101,
          150,
          197,
          80
        ],
        "backgroundColor": "#3b82f6",
        "borderRadius": 4
      }
    ]
  }
}