{
  "title": "Voter Age Distribution by Birth Decade — KETTERING 4-H",
  "county": "Montgomery",
  "precinct": "KETTERING 4-H",
  "geography": "precinct-detail",
  "type": "bar",
  "updated": "2026-06-22",
  "chartConfig": {
    "labels": [
      "1930s",
      "1940s",
      "1950s",
      "1960s",
      "1970s",
      "1980s",
      "1990s",
      "2000s"
    ],
    "datasets": [
      {
        "label": "Registered Voters",
        "data": [
          15,
          55,
          106,
          108,
          125,
          186,
          162,
          106
        ],
        "backgroundColor": "#3b82f6",
        "borderRadius": 4
      }
    ]
  }
}