{
  "title": "Party Affiliation \u2014 PRECINCT HUNTINGTON SOUTH",
  "county": "Ross",
  "precinct": "PRECINCT HUNTINGTON SOUTH",
  "geography": "precinct-detail",
  "type": "doughnut",
  "updated": "2026-05-06",
  "chartConfig": {
    "labels": [
      "REP",
      "UNC \u2013 Lifetime R",
      "DEM",
      "UNC \u2013 Lifetime D",
      "UNC \u2013 Mixed",
      "UNC \u2013 No History"
    ],
    "datasets": [
      {
        "data": [
          122,
          60,
          22,
          92,
          34,
          402
        ],
        "backgroundColor": [
          "#ef4444",
          "#f87171",
          "#3b82f6",
          "#60a5fa",
          "#a78bfa",
          "#9ca3af"
        ],
        "borderWidth": 2,
        "borderColor": "transparent"
      }
    ]
  }
}