{
  "title": "Party Affiliation by Generation \u2014 FREMONT CITY 3-B",
  "county": "Sandusky",
  "precinct": "FREMONT CITY 3-B",
  "geography": "precinct-detail",
  "type": "bar",
  "updated": "2026-05-07",
  "note": "Pew Research Center generational boundaries",
  "chartConfig": {
    "labels": [
      "Silent/Greatest",
      "Baby Boomers",
      "Gen X",
      "Millennials",
      "Gen Z"
    ],
    "datasets": [
      {
        "label": "REP",
        "data": [
          45,
          104,
          55,
          14,
          11
        ],
        "backgroundColor": "#ef4444",
        "borderRadius": 2,
        "stack": "rep"
      },
      {
        "label": "DEM",
        "data": [
          17,
          63,
          13,
          9,
          4
        ],
        "backgroundColor": "#3b82f6",
        "borderRadius": 2,
        "stack": "dem"
      },
      {
        "label": "Other",
        "data": [
          0,
          0,
          0,
          0,
          0
        ],
        "backgroundColor": "#f59e0b",
        "borderRadius": 2,
        "stack": "other"
      },
      {
        "label": "UNC \u2013 Lifetime D",
        "data": [
          13,
          35,
          31,
          29,
          2
        ],
        "backgroundColor": "#60a5fa",
        "borderRadius": 2,
        "stack": "unc"
      },
      {
        "label": "UNC \u2013 Lifetime R",
        "data": [
          8,
          23,
          28,
          24,
          6
        ],
        "backgroundColor": "#f87171",
        "borderRadius": 2,
        "stack": "unc"
      },
      {
        "label": "UNC \u2013 Mixed",
        "data": [
          14,
          41,
          26,
          33,
          1
        ],
        "backgroundColor": "#a78bfa",
        "borderRadius": 2,
        "stack": "unc"
      },
      {
        "label": "UNC \u2013 No History",
        "data": [
          7,
          48,
          83,
          139,
          139
        ],
        "backgroundColor": "#9ca3af",
        "borderRadius": 2,
        "stack": "unc"
      }
    ]
  }
}