{
  "title": "Party Affiliation by Birth Decade — HAMILTON TWP E",
  "county": "Warren",
  "precinct": "HAMILTON TWP E",
  "geography": "precinct-detail",
  "type": "bar",
  "updated": "2026-05-09",
  "chartConfig": {
    "labels": [
      "1920s",
      "1930s",
      "1940s",
      "1950s",
      "1960s",
      "1970s",
      "1980s",
      "1990s",
      "2000s"
    ],
    "datasets": [
      {
        "label": "Pure R",
        "data": [
          0,
          6,
          44,
          50,
          31,
          16,
          26,
          3,
          9
        ],
        "backgroundColor": "#ef4444",
        "borderRadius": 3,
        "stack": "r_pure"
      },
      {
        "label": "UNC – Lapsed R",
        "data": [
          0,
          3,
          17,
          32,
          40,
          42,
          25,
          17,
          0
        ],
        "backgroundColor": "#fca5a5",
        "borderRadius": 3,
        "stack": "unc_r"
      },
      {
        "label": "Mixed – Active",
        "data": [
          0,
          2,
          18,
          27,
          14,
          6,
          3,
          1,
          0
        ],
        "backgroundColor": "#f59e0b",
        "borderRadius": 3,
        "stack": "unc_mid"
      },
      {
        "label": "Mixed – Lapsed",
        "data": [
          1,
          2,
          9,
          21,
          19,
          23,
          18,
          5,
          1
        ],
        "backgroundColor": "#a78bfa",
        "borderRadius": 3,
        "stack": "unc_mid"
      },
      {
        "label": "UNC – No Primary",
        "data": [
          0,
          1,
          12,
          20,
          51,
          56,
          87,
          113,
          92
        ],
        "backgroundColor": "#9ca3af",
        "borderRadius": 3,
        "stack": "unc_mid"
      },
      {
        "label": "UNC – Lapsed D",
        "data": [
          0,
          0,
          10,
          15,
          18,
          23,
          30,
          20,
          1
        ],
        "backgroundColor": "#93c5fd",
        "borderRadius": 3,
        "stack": "unc_d"
      },
      {
        "label": "Pure D",
        "data": [
          1,
          4,
          8,
          11,
          2,
          6,
          1,
          7,
          6
        ],
        "backgroundColor": "#3b82f6",
        "borderRadius": 3,
        "stack": "d_pure"
      }
    ]
  }
}