{
  "geography": "precinct",
  "level": "precinct",
  "jurisdiction_name": "FRANKLIN TWP H",
  "updated": "2026-07-15",
  "generated_by": "templated-v1",
  "template_version": "v2",
  "config_version": "v1",
  "metrics_hash": "a99450f55cb00908",
  "narrative": "Franklin Twp H (precinct in Warren County) has 889 registered voters, with 61.0% unaffiliated or lacking primary history. Republican-leaning voters make up 25.2% of registrants and Democratic-leaning voters account for 13.8%, a clear Republican lean of 11.4 percentage points.\n\nElected representation:\n  Republican Precinct Captain: data not yet available.\n  Democratic Precinct Captain: data not yet available."
}