{
  "geography": "precinct",
  "level": "precinct",
  "jurisdiction_name": "WASHINGTON TWP",
  "updated": "2026-07-14",
  "generated_by": "templated-v1",
  "template_version": "v2",
  "config_version": "v1",
  "metrics_hash": "7dc029426b486240",
  "narrative": "Washington Twp (precinct in Wood County) has 1,187 registered voters, with 43.1% unaffiliated or lacking primary history. Republican-leaning voters make up 39.7% of registrants and Democratic-leaning voters account for 17.2%, a pronounced Republican lean of 22.5 percentage points.\n\nElected representation:\n  Republican Precinct Captain: data not yet available.\n  Democratic Precinct Captain: data not yet available."
}