{
  "title": "UNC Shadow Partisanship",
  "type": "doughnut",
  "chartConfig": {
    "labels": [
      "UNC – Lapsed R — 1,396",
      "Mixed – Active — 1,060",
      "Mixed – Lapsed — 1,068",
      "UNC – No Primary — 3,496",
      "UNC – Lapsed D — 1,091"
    ],
    "datasets": [
      {
        "data": [
          1396,
          1060,
          1068,
          3496,
          1091
        ],
        "backgroundColor": [
          "#fca5a5",
          "#f59e0b",
          "#a78bfa",
          "#9ca3af",
          "#93c5fd"
        ]
      }
    ]
  },
  "note": "Analysis run 2026-07-10 — Ohio Secretary of State SWVF voter file",
  "geography": "Exempted Village School District",
  "jurisdiction_name": "GRANVILLE EX VILL SD (LICKING)",
  "updated": "2026-07-10"
}